{
	"info": {
		"_postman_id": "e75f43d8-e530-4b8c-88cb-dbf21d33a188",
		"name": "micronaut-product",
		"schema": "https://schema.getpostman.com/json/collection/v2.1.0/collection.json",
		"_exporter_id": "6166502"
	},
	"item": [
		{
			"name": "save",
			"request": {
				"method": "POST",
				"header": [],
				"body": {
					"mode": "raw",
					"raw": "{    \n    \"product\": \"Jogo do Mario Deluxe\",\n    \"idCategory\": 2,\n    \"price\": 99.99,\n    \"total\": 200,\n    \"created\": \"2024-08-27T15:00:00\",\n    \"updated\": \"2024-08-27T15:30:00\",\n    \"active\": true\n}",
					"options": {
						"raw": {
							"language": "json"
						}
					}
				},
				"url": {
					"raw": "http://localhost:9000/product",
					"protocol": "http",
					"host": [
						"localhost"
					],
					"port": "9000",
					"path": [
						"product"
					]
				}
			},
			"response": []
		},
		{
			"name": "update",
			"request": {
				"method": "PUT",
				"header": [],
				"body": {
					"mode": "raw",
					"raw": "{    \n    \"product\": \"Jogo do Sonic 4\",\n    \"idCategory\": 2,\n    \"price\": 99.99,\n    \"total\": 200,\n    \"created\": \"2024-08-27T15:00:00\",\n    \"updated\": \"2024-08-27T15:30:00\",\n    \"active\": false\n}",
					"options": {
						"raw": {
							"language": "json"
						}
					}
				},
				"url": {
					"raw": "http://localhost:9000/product/4",
					"protocol": "http",
					"host": [
						"localhost"
					],
					"port": "9000",
					"path": [
						"product",
						"4"
					]
				}
			},
			"response": []
		},
		{
			"name": "reduce stock",
			"request": {
				"method": "PUT",
				"header": [],
				"body": {
					"mode": "raw",
					"raw": "{    \n    \"product\": \"Jogo do Sonic 4\",\n    \"idCategory\": 2,\n    \"price\": 99.99,\n    \"total\": 200,\n    \"created\": \"2024-08-27T15:00:00\",\n    \"updated\": \"2024-08-27T15:30:00\",\n    \"active\": false\n}",
					"options": {
						"raw": {
							"language": "json"
						}
					}
				},
				"url": {
					"raw": "http://localhost:9000/product/4/reduce/stock",
					"protocol": "http",
					"host": [
						"localhost"
					],
					"port": "9000",
					"path": [
						"product",
						"4",
						"reduce",
						"stock"
					]
				}
			},
			"response": []
		},
		{
			"name": "findAll",
			"request": {
				"method": "GET",
				"header": [],
				"url": {
					"raw": "http://localhost:9000/product/findAll",
					"protocol": "http",
					"host": [
						"localhost"
					],
					"port": "9000",
					"path": [
						"product",
						"findAll"
					]
				}
			},
			"response": []
		},
		{
			"name": "findbyId",
			"request": {
				"method": "GET",
				"header": [],
				"url": {
					"raw": "http://localhost:9000/product/4",
					"protocol": "http",
					"host": [
						"localhost"
					],
					"port": "9000",
					"path": [
						"product",
						"4"
					]
				}
			},
			"response": []
		},
		{
			"name": "delete",
			"request": {
				"method": "DELETE",
				"header": [],
				"url": {
					"raw": "http://localhost:9000/product/1",
					"protocol": "http",
					"host": [
						"localhost"
					],
					"port": "9000",
					"path": [
						"product",
						"1"
					]
				}
			},
			"response": []
		}
	]
}